<dataStore>
  <id>DataStoreInfoImpl--285b7e02:14d4812a9f4:-7ffd</id>
  <name>crimedata</name>
  <description>Indicent reports</description>
  <type>PostGIS</type>
  <enabled>true</enabled>
  <workspace>
    <id>WorkspaceInfoImpl--285b7e02:14d4812a9f4:-7fff</id>
  </workspace>
  <connectionParameters>
    <entry key="Evictor run periodicity">300</entry>
    <entry key="schema">public</entry>
    <entry key="Max open prepared statements">50</entry>
    <entry key="encode functions">false</entry>
    <entry key="preparedStatements">false</entry>
    <entry key="database">crimedata</entry>
    <entry key="host">localhost</entry>
    <entry key="Loose bbox">true</entry>
    <entry key="Estimated extends">true</entry>
    <entry key="fetch size">50000</entry>
    <entry key="validate connections">true</entry>
    <entry key="Support on the fly geometry simplification">true</entry>
    <entry key="Expose primary keys">false</entry>
    <entry key="Connection timeout">20</entry>
    <entry key="create database">false</entry>
    <entry key="port">5432</entry>
    <entry key="passwd">crypt1:lohK7rOeoCqA/s2nJT7g85v4TbhgKmer</entry>
    <entry key="min connections">1</entry>
    <entry key="dbtype">postgis</entry>
    <entry key="namespace">http://localhost</entry>
    <entry key="Evictor tests per run">3</entry>
    <entry key="max connections">10</entry>
    <entry key="Test while idle">true</entry>
    <entry key="user">postgres</entry>
    <entry key="Max connection idle time">300</entry>
  </connectionParameters>
  <__default>false</__default>
</dataStore>